scargo/__init__.py
scargo/cli.py
scargo/config.py
scargo/config_utils.py
scargo/global_values.py
scargo/logger.py
scargo/certs/certGen.sh
scargo/certs/generateAllCertificates.sh
scargo/certs/openssl_device_intermediate_ca.cnf
scargo/certs/openssl_root_ca.cnf
scargo/commands/__init__.py
scargo/commands/build.py
scargo/commands/check.py
scargo/commands/clean.py
scargo/commands/debug.py
scargo/commands/doc.py
scargo/commands/docker.py
scargo/commands/fix.py
scargo/commands/flash.py
scargo/commands/gen.py
scargo/commands/license_check.py
scargo/commands/monitor.py
scargo/commands/new.py
scargo/commands/publish.py
scargo/commands/run.py
scargo/commands/test.py
scargo/commands/update.py
scargo/commands/version.py
scargo/file_generators/__init__.py
scargo/file_generators/base_gen.py
scargo/file_generators/cicd_gen.py
scargo/file_generators/cmake_gen.py
scargo/file_generators/conan_gen.py
scargo/file_generators/cpp_gen.py
scargo/file_generators/docker_gen.py
scargo/file_generators/env_gen.py
scargo/file_generators/mock_gen.py
scargo/file_generators/readme_gen.py
scargo/file_generators/tests_gen.py
scargo/file_generators/toml_gen.py
scargo/file_generators/ut_gen.py
scargo/file_generators/vscode_gen.py
scargo/file_generators/clang_parser/__init__.py
scargo/file_generators/clang_parser/data_classes.py
scargo/file_generators/clang_parser/header_parser.py
scargo/file_generators/clang_parser/params_extractor.py
scargo/file_generators/templates/.gitlab-ci-custom.yml.j2
scargo/file_generators/templates/.gitlab-ci.yml.j2
scargo/file_generators/templates/CMakeLists.txt.j2
scargo/file_generators/templates/README.md.j2
scargo/file_generators/templates/scargo.toml.j2
scargo/file_generators/templates/conan/conanfile.py.j2
scargo/file_generators/templates/conan/conanfiletest.j2
scargo/file_generators/templates/conan/profile_atsam.j2
scargo/file_generators/templates/conan/profile_esp32.j2
scargo/file_generators/templates/conan/profile_stm32.j2
scargo-3.2.3.dist-info/entry_points.txt
scargo-3.2.3.dist-info/LICENSE
scargo-3.2.3.dist-info/WHEEL
scargo-3.2.3.dist-info/METADATA
scargo-3.2.3.dist-info/RECORD
