Metadata-Version: 2.1
Name: scargo
Version: 3.2.3
Summary: C/C++ package and software development life cycle manager inspired by RUST cargo idea.
Keywords: scargo,Package manager,C++
Author-email: "Spyrosoft Solutions S.A." <aak@spyro-soft.com>, Andrzej Aksenczuk <andrzej.aksenczuk@gmail.com>
Requires-Python: >=3.8
Classifier: Development Status :: 5 - Production/Stable
Classifier: Intended Audience :: Developers
Classifier: Natural Language :: English
Classifier: Operating System :: POSIX
Classifier: Operating System :: Microsoft :: Windows
Classifier: Operating System :: MacOS :: MacOS X
Classifier: Topic :: Software Development :: Embedded Systems
Classifier: Environment :: Console
Classifier: License :: OSI Approved :: MIT License
Classifier: Programming Language :: Python :: 3.8
Classifier: Programming Language :: Python :: 3.9
Classifier: Programming Language :: Python :: 3.10
Requires-Dist: clang==17.0.6
Requires-Dist: cmake==3.30.5
Requires-Dist: coloredlogs==15.0.1
Requires-Dist: conan==2.8.1
Requires-Dist: docker==7.1.0
Requires-Dist: esptool==4.7.0
Requires-Dist: gcovr==8.2
Requires-Dist: jinja2==3.1.4
Requires-Dist: libclang==18.1.1
Requires-Dist: lizard==1.17.10
Requires-Dist: pydantic==1.10.6
Requires-Dist: toml==0.10.2
Requires-Dist: tomlkit==0.13.2
Requires-Dist: typer==0.9.0
Requires-Dist: click==8.1.3
Requires-Dist: typing-extensions==4.6.0
Requires-Dist: paramiko==3.5.0
Requires-Dist: pyyaml==6.0.2
Requires-Dist: black==24.8.0 ; extra == "dev"
Requires-Dist: coverage~=7.6.1 ; extra == "dev"
Requires-Dist: flake8>=6.1.0 ; extra == "dev"
Requires-Dist: flit==3.8.0 ; extra == "dev"
Requires-Dist: isort==5.11.4 ; extra == "dev"
Requires-Dist: matplotlib==3.7.5 ; extra == "dev"
Requires-Dist: mypy==1.14.1 ; extra == "dev"
Requires-Dist: numpy>=1.26.0 ; extra == "dev"
Requires-Dist: pre-commit ; extra == "dev"
Requires-Dist: pyclean==3.0.0 ; extra == "dev"
Requires-Dist: pyelftools ; extra == "dev"
Requires-Dist: pyfakefs==5.3.2 ; extra == "dev"
Requires-Dist: pylint==3.2.7 ; extra == "dev"
Requires-Dist: pytest-cov==4.1.0 ; extra == "dev"
Requires-Dist: pytest-mock==3.12.0 ; extra == "dev"
Requires-Dist: pytest-subprocess==1.5.0 ; extra == "dev"
Requires-Dist: pytest==7.4.3 ; extra == "dev"
Requires-Dist: pytest-lazy-fixture==0.6.3 ; extra == "dev"
Requires-Dist: pytest-xdist==3.5.0 ; extra == "dev"
Requires-Dist: pytest-order==1.2.0 ; extra == "dev"
Requires-Dist: types-clang==0.14.3 ; extra == "dev"
Requires-Dist: types-toml ; extra == "dev"
Requires-Dist: unittest-xml-reporting ; extra == "dev"
Requires-Dist: pyopenssl==23.2.0 ; extra == "dev"
Requires-Dist: types-pyOpenSSL==23.2.0 ; extra == "dev"
Requires-Dist: types-PyYAML==6.0.12.12 ; extra == "dev"
Requires-Dist: pip-tools==7.4.1 ; extra == "dev"
Requires-Dist: recommonmark ; extra == "doc"
Requires-Dist: sphinx-rtd-theme==1.1.1 ; extra == "doc"
Requires-Dist: Sphinx ; extra == "doc"
Requires-Dist: sphinxcontrib-plantuml==0.30 ; extra == "doc"
Project-URL: Documentation, https://spyro-soft.github.io/scargo/index.html
Project-URL: Source, https://github.com/spyro-soft/scargo
Project-URL: Tracker, https://github.com/Spyro-Soft/scargo/issues
Provides-Extra: dev
Provides-Extra: doc
